{"data":{"propertyOrder":{},"properties":{"idProdus":{"name":"idProdus","reference":"scalar","primary":true,"unsigned":true,"autoincrement":true,"type":"number"},"eanProdus":{"name":"eanProdus","reference":"scalar","unsigned":true,"unique":true,"nullable":false,"getter":false,"setter":false,"type":"bigint"},"numeProdus":{"name":"numeProdus","reference":"scalar","unique":true,"nullable":false,"getter":false,"setter":false,"type":"string"},"createdAt":{"name":"createdAt","reference":"scalar","getter":false,"setter":false,"type":"Date"},"updatedAt":{"name":"updatedAt","reference":"scalar","getter":false,"setter":false,"type":"Date"}},"props":[{"name":"idProdus","reference":"scalar","primary":true,"unsigned":true,"autoincrement":true,"type":"number"},{"name":"eanProdus","reference":"scalar","unsigned":true,"unique":true,"nullable":false,"getter":false,"setter":false,"type":"bigint"},{"name":"numeProdus","reference":"scalar","unique":true,"nullable":false,"getter":false,"setter":false,"type":"string"},{"name":"createdAt","reference":"scalar","getter":false,"setter":false,"type":"Date"},{"name":"updatedAt","reference":"scalar","getter":false,"setter":false,"type":"Date"}],"primaryKeys":["idProdus"],"filters":{},"hooks":{},"indexes":[{"properties":["numeProdus","eanProdus"]},{"properties":["eanProdus","numeProdus"]}],"uniques":[],"checks":[],"concurrencyCheckKeys":{},"className":"Produs","path":"./dist/produse/Produs.entity.js","name":"Produs","abstract":false,"constructorParams":["numeProdus","eanProdus"],"toJsonParams":[],"useCache":true,"compositePK":false,"relations":[],"collection":"produs"},"origin":"./dist/produse/Produs.entity.js","hash":"4b2c15e91ce544cf72ff6fdf9cdb3114","version":"5.2.1"}
